woopac/__init__.py
woopac/__main__.py
woopac/app/__init__.py
woopac/app/app.py
woopac/utils/__init__.py
woopac/utils/exceptions.py
woopac/utils/functions.py
woopac1-1.0.0.dist-info/LICENSE
woopac1-1.0.0.dist-info/METADATA
woopac1-1.0.0.dist-info/WHEEL
woopac1-1.0.0.dist-info/entry_points.txt
woopac1-1.0.0.dist-info/top_level.txt
woopac1-1.0.0.dist-info/RECORD
